mtbs/__init__.py
mtbs/cli.py
mtbs/mcp_server.py
mtbs/mtbs.py
mtbs/py.typed
mtbs/sql.py
mtbs/test.py
mtbs-0.1.10.dist-info/METADATA
mtbs-0.1.10.dist-info/WHEEL
mtbs-0.1.10.dist-info/entry_points.txt
mtbs-0.1.10.dist-info/RECORD
