Metadata-Version: 2.4
Name: mtbs
Version: 0.1.10
Summary: a little lib to interact with Metabase
Author-email: Ruddy <ruddy.at.work@proton.me>
Requires-Python: >=3.12.8
Requires-Dist: alive-progress>=3.2.0
Requires-Dist: click==8.1.7
Requires-Dist: diskcache>=5.6.3
Requires-Dist: mcp[cli]>=1.11.0
Requires-Dist: opentelemetry-api>=1.34.1
Requires-Dist: opentelemetry-sdk>=1.34.1
Requires-Dist: pandas>=2.3.1
Requires-Dist: plotly>=6.2.0
Requires-Dist: questionary>=2.1.0
Requires-Dist: requests==2.31.0
Requires-Dist: streamlit>=1.47.0
Requires-Dist: tabulate>=0.9.0
